pdfplucker/__init__.py
pdfplucker/cli.py
pdfplucker/core.py
pdfplucker/processor.py
pdfplucker/utils.py
pdfplucker-1.1.3.dist-info/LICENSE.txt
pdfplucker-1.1.3.dist-info/METADATA
pdfplucker-1.1.3.dist-info/WHEEL
pdfplucker-1.1.3.dist-info/entry_points.txt
pdfplucker-1.1.3.dist-info/RECORD
