Metadata-Version: 2.3
Name: pdfplucker
Version: 1.1.3
Summary: Docling wrapper for PDF parsing
License: MIT
Keywords: docling,pdf,ocr,parser
Author: rafaelghiorzi
Author-email: rafael.ghiorzi@gmail.com
Requires-Python: >=3.12,<3.13
Classifier: Development Status :: 5 - Production/Stable
Classifier: Intended Audience :: Developers
Classifier: Intended Audience :: Science/Research
Classifier: License :: OSI Approved :: MIT License
Classifier: Natural Language :: English
Classifier: Operating System :: Microsoft :: Windows
Classifier: Programming Language :: Python :: 3
Classifier: Programming Language :: Python :: 3.12
Requires-Dist: PyMuPDF (>=1.25.5,<2.0.0)
Requires-Dist: docling (>=2.30.0,<3.0.0)
Requires-Dist: psutil (>=7.0.0,<8.0.0)
Requires-Dist: torch (>=2.6.0,<3.0.0)
Project-URL: Bug Tracker, https://github.com/ipeadata-lab/pdfplucker/issues
Project-URL: Homepage, https://github.com/ipeadata-lab/pdfplucker
Project-URL: Repository, https://github.com/ipeadata-lab/pdfplucker
